chebpy/__init__.py
chebpy/api.py
chebpy/core/__init__.py
chebpy/core/algorithms.py
chebpy/core/bndfun.py
chebpy/core/chebfun.py
chebpy/core/chebtech.py
chebpy/core/classicfun.py
chebpy/core/decorators.py
chebpy/core/exceptions.py
chebpy/core/ffts.py
chebpy/core/fun.py
chebpy/core/importing.py
chebpy/core/onefun.py
chebpy/core/plotting.py
chebpy/core/settings.py
chebpy/core/smoothfun.py
chebpy/core/utilities.py
chebfun-0.4.4.1.dist-info/METADATA
chebfun-0.4.4.1.dist-info/WHEEL
chebfun-0.4.4.1.dist-info/licenses/LICENSE.rst
chebfun-0.4.4.1.dist-info/RECORD
