Metadata-Version: 2.4
Name: chebfun
Version: 0.4.4.1
Summary: A Python implementation of Chebfun
Project-URL: repository, https://github.com/chebpy/chebpy
Author-email: Mark Richardson <mrichardson82@gmail.com>
License-File: LICENSE.rst
Requires-Python: >=3.10
Requires-Dist: numpy>=2.0
Provides-Extra: dev
Requires-Dist: matplotlib==3.10.0; extra == 'dev'
Requires-Dist: pre-commit>=4.2.0; extra == 'dev'
Requires-Dist: pytest-cov>=6.2.1; extra == 'dev'
Requires-Dist: pytest>=8.4.1; extra == 'dev'
